LICENSE
MANIFEST.in
README.rst
setup.py
tipi/__init__.py
tipi/compat.py
tipi/html.py
tipi/repl.py
tipi.egg-info/PKG-INFO
tipi.egg-info/SOURCES.txt
tipi.egg-info/dependency_links.txt
tipi.egg-info/not-zip-safe
tipi.egg-info/requires.txt
tipi.egg-info/top_level.txt
tipi/langs/__init__.py
tipi/langs/base.py
tipi/langs/cs.py
tipi/langs/de.py
tipi/langs/en.py
tipi/langs/fr.py
tipi/langs/pl.py