Metadata-Version: 1.1
Name: tipi
Version: 0.0.3
Summary: Typographic replacements in HTML
Home-page: https://github.com/honzajavorek/tipi
Author: Honza Javorek
Author-email: mail@honzajavorek.cz
License: The MIT License (MIT)
